[
  {
    "id": 2,
    "text": "name",
    "prefixKey": null,
    "suffixKey": null,
    "backgroundColor": "#73D8FF",
    "textColor": "#ffffff"
  },
  {
    "id": 3,
    "text": "phone",
    "prefixKey": null,
    "suffixKey": null,
    "backgroundColor": "#0062B1",
    "textColor": "#ffffff"
  },
  {
    "id": 4,
    "text": "email",
    "prefixKey": null,
    "suffixKey": null,
    "backgroundColor": "#194D33",
    "textColor": "#ffffff"
  },
  {
    "id": 5,
    "text": "role",
    "prefixKey": null,
    "suffixKey": null,
    "backgroundColor": "#9F0500",
    "textColor": "#ffffff"
  },
  {
    "id": 6,
    "text": "experience",
    "prefixKey": null,
    "suffixKey": null,
    "backgroundColor": "#FDA1FF",
    "textColor": "#ffffff"
  },
  {
    "id": 7,
    "text": "skills",
    "prefixKey": null,
    "suffixKey": null,
    "backgroundColor": "#c4deb8",
    "textColor": "#ffffff"
  },
  {
    "id": 8,
    "text": "companies",
    "prefixKey": null,
    "suffixKey": null,
    "backgroundColor": "#F44E3B",
    "textColor": "#ffffff"
  },
  {
    "id": 9,
    "text": "languages",
    "prefixKey": null,
    "suffixKey": null,
    "backgroundColor": "#0C797D",
    "textColor": "#ffffff"
  },
  {
    "id": 10,
    "text": "acheivements",
    "prefixKey": null,
    "suffixKey": null,
    "backgroundColor": "#59DF49",
    "textColor": "#ffffff"
  },
  {
    "id": 11,
    "text": "education",
    "prefixKey": null,
    "suffixKey": null,
    "backgroundColor": "#FCDC00",
    "textColor": "#ffffff"
  }
]